[{"divisionCode":130103001,"post":"050011","divisionName":"中山东路街道","isLeaf":1},{"divisionCode":130103002,"post":"050011","divisionName":"彭后街道","isLeaf":1},{"divisionCode":130103003,"post":"050011","divisionName":"东风街道","isLeaf":1},{"divisionCode":130103004,"post":"050011","divisionName":"东华街道","isLeaf":1},{"divisionCode":130103005,"post":"050011","divisionName":"休门街道","isLeaf":1},{"divisionCode":130103006,"post":"050011","divisionName":"阜康街道","isLeaf":1},{"divisionCode":130103007,"post":"050011","divisionName":"建安街道","isLeaf":1},{"divisionCode":130103008,"post":"050011","divisionName":"胜利北街道","isLeaf":1},{"divisionCode":130103009,"post":"050011","divisionName":"汇通街道","isLeaf":1},{"divisionCode":130103101,"post":"050011","divisionName":"桃园镇","isLeaf":1}]