[{"divisionCode":130624100,"post":"073200","divisionName":"阜平镇","isLeaf":1},{"divisionCode":130624101,"post":"073200","divisionName":"龙泉关镇","isLeaf":1},{"divisionCode":130624102,"post":"073200","divisionName":"平阳镇","isLeaf":1},{"divisionCode":130624103,"post":"073200","divisionName":"城南庄镇","isLeaf":1},{"divisionCode":130624104,"post":"073200","divisionName":"天生桥镇","isLeaf":1},{"divisionCode":130624201,"post":"073200","divisionName":"王林口乡","isLeaf":1},{"divisionCode":130624202,"post":"073200","divisionName":"台峪乡","isLeaf":1},{"divisionCode":130624203,"post":"073200","divisionName":"大台乡","isLeaf":1},{"divisionCode":130624204,"post":"073200","divisionName":"史家寨乡","isLeaf":1},{"divisionCode":130624205,"post":"073200","divisionName":"砂窝乡","isLeaf":1},{"divisionCode":130624206,"post":"073200","divisionName":"吴王口乡","isLeaf":1},{"divisionCode":130624207,"post":"073200","divisionName":"夏庄乡","isLeaf":1},{"divisionCode":130624208,"post":"073200","divisionName":"北果元乡","isLeaf":1}]