[{"divisionCode":130683001,"post":"071200","divisionName":"祁州药市街道","isLeaf":1},{"divisionCode":130683100,"post":"071200","divisionName":"祁州镇","isLeaf":1},{"divisionCode":130683101,"post":"071200","divisionName":"伍仁桥镇","isLeaf":1},{"divisionCode":130683102,"post":"071200","divisionName":"石佛镇","isLeaf":1},{"divisionCode":130683103,"post":"071200","divisionName":"郑章镇","isLeaf":1},{"divisionCode":130683104,"post":"071200","divisionName":"大五女镇","isLeaf":1},{"divisionCode":130683105,"post":"071200","divisionName":"西佛落镇","isLeaf":1},{"divisionCode":130683200,"post":"071200","divisionName":"明官店乡","isLeaf":1},{"divisionCode":130683201,"post":"071200","divisionName":"南娄底乡","isLeaf":1},{"divisionCode":130683202,"post":"071200","divisionName":"西安国城乡","isLeaf":1},{"divisionCode":130683204,"post":"071200","divisionName":"北段村乡","isLeaf":1}]