[{"divisionCode":130923100,"post":"061600","divisionName":"东光镇","isLeaf":1},{"divisionCode":130923101,"post":"061600","divisionName":"连镇镇","isLeaf":1},{"divisionCode":130923102,"post":"061600","divisionName":"找王镇","isLeaf":1},{"divisionCode":130923103,"post":"061600","divisionName":"秦村镇","isLeaf":1},{"divisionCode":130923104,"post":"061600","divisionName":"灯明寺镇","isLeaf":1},{"divisionCode":130923105,"post":"061600","divisionName":"南霞口镇","isLeaf":1},{"divisionCode":130923106,"post":"061600","divisionName":"大单镇","isLeaf":1},{"divisionCode":130923107,"post":"061600","divisionName":"龙王李镇","isLeaf":1},{"divisionCode":130923201,"post":"061600","divisionName":"于桥乡","isLeaf":1}]