[{"divisionCode":141129100,"post":"033400","divisionName":"宁乡镇","isLeaf":1},{"divisionCode":141129101,"post":"033400","divisionName":"金罗镇","isLeaf":1},{"divisionCode":141129102,"post":"033400","divisionName":"枝柯镇","isLeaf":1},{"divisionCode":141129103,"post":"033400","divisionName":"武家庄镇","isLeaf":1},{"divisionCode":141129104,"post":"033400","divisionName":"暖泉镇","isLeaf":1},{"divisionCode":141129200,"post":"033400","divisionName":"张子山乡","isLeaf":1},{"divisionCode":141129201,"post":"033400","divisionName":"下枣林乡","isLeaf":1}]