[{"divisionCode":150826100,"post":"015400","divisionName":"陕坝镇","isLeaf":1},{"divisionCode":150826101,"post":"015400","divisionName":"头道桥镇","isLeaf":1},{"divisionCode":150826102,"post":"015400","divisionName":"二道桥镇","isLeaf":1},{"divisionCode":150826103,"post":"015400","divisionName":"三道桥镇","isLeaf":1},{"divisionCode":150826104,"post":"015400","divisionName":"蛮会镇","isLeaf":1},{"divisionCode":150826105,"post":"015400","divisionName":"团结镇","isLeaf":1},{"divisionCode":150826106,"post":"015400","divisionName":"双庙镇","isLeaf":1},{"divisionCode":150826107,"post":"015400","divisionName":"沙海镇","isLeaf":1},{"divisionCode":150826108,"post":"015400","divisionName":"蒙海镇","isLeaf":1},{"divisionCode":150826500,"post":"015400","divisionName":"太阳庙农场","isLeaf":1}]