[{"divisionCode":230381100,"post":"158400","divisionName":"虎林镇","isLeaf":1},{"divisionCode":230381101,"post":"158400","divisionName":"东方红镇","isLeaf":1},{"divisionCode":230381102,"post":"158400","divisionName":"迎春镇","isLeaf":1},{"divisionCode":230381103,"post":"158400","divisionName":"虎头镇","isLeaf":1},{"divisionCode":230381104,"post":"158400","divisionName":"杨岗镇","isLeaf":1},{"divisionCode":230381105,"post":"158400","divisionName":"东诚镇","isLeaf":1},{"divisionCode":230381106,"post":"158400","divisionName":"宝东镇","isLeaf":1},{"divisionCode":230381203,"post":"158400","divisionName":"新乐乡","isLeaf":1},{"divisionCode":230381204,"post":"158400","divisionName":"伟光乡","isLeaf":1},{"divisionCode":230381206,"post":"158400","divisionName":"珍宝岛乡","isLeaf":1},{"divisionCode":230381207,"post":"158400","divisionName":"阿北乡","isLeaf":1},{"divisionCode":230381400,"post":"158400","divisionName":"东方红林业局","isLeaf":1},{"divisionCode":230381401,"post":"158400","divisionName":"迎春林业局","isLeaf":1},{"divisionCode":230381500,"post":"158400","divisionName":"八五０农场","isLeaf":1},{"divisionCode":230381501,"post":"158400","divisionName":"八五四农场","isLeaf":1},{"divisionCode":230381502,"post":"158400","divisionName":"八五六农场","isLeaf":1},{"divisionCode":230381503,"post":"158400","divisionName":"八五八农场","isLeaf":1},{"divisionCode":230381504,"post":"158400","divisionName":"庆丰农场","isLeaf":1},{"divisionCode":230381505,"post":"158400","divisionName":"云山农场","isLeaf":1}]