[{"divisionCode":230781100,"post":"152500","divisionName":"铁力镇","isLeaf":1},{"divisionCode":230781101,"post":"152500","divisionName":"双丰镇","isLeaf":1},{"divisionCode":230781102,"post":"152500","divisionName":"桃山镇","isLeaf":1},{"divisionCode":230781104,"post":"152500","divisionName":"朗乡镇","isLeaf":1},{"divisionCode":230781200,"post":"152500","divisionName":"年丰乡","isLeaf":1},{"divisionCode":230781201,"post":"152500","divisionName":"工农乡","isLeaf":1},{"divisionCode":230781202,"post":"152500","divisionName":"王杨乡","isLeaf":1},{"divisionCode":230781400,"post":"152500","divisionName":"铁力林业局","isLeaf":1},{"divisionCode":230781401,"post":"152500","divisionName":"双丰林业局","isLeaf":1},{"divisionCode":230781402,"post":"152500","divisionName":"桃山林业局","isLeaf":1},{"divisionCode":230781403,"post":"152500","divisionName":"朗乡林业局","isLeaf":1},{"divisionCode":230781500,"post":"152500","divisionName":"铁力农场","isLeaf":1}]