[{"divisionCode":231083100,"post":"157100","divisionName":"海林镇","isLeaf":1},{"divisionCode":231083101,"post":"157100","divisionName":"长汀镇","isLeaf":1},{"divisionCode":231083102,"post":"157100","divisionName":"横道镇","isLeaf":1},{"divisionCode":231083103,"post":"157100","divisionName":"山市镇","isLeaf":1},{"divisionCode":231083104,"post":"157100","divisionName":"柴河镇","isLeaf":1},{"divisionCode":231083105,"post":"157100","divisionName":"二道镇","isLeaf":1},{"divisionCode":231083106,"post":"157100","divisionName":"新安朝鲜族镇","isLeaf":1},{"divisionCode":231083107,"post":"157100","divisionName":"三道镇","isLeaf":1},{"divisionCode":231083400,"post":"157100","divisionName":"牡林工程公司街道","isLeaf":1},{"divisionCode":231083401,"post":"157100","divisionName":"柴河林机厂街道","isLeaf":1},{"divisionCode":231083402,"post":"157100","divisionName":"大海林林业局","isLeaf":1},{"divisionCode":231083403,"post":"157100","divisionName":"海林林业局","isLeaf":1},{"divisionCode":231083404,"post":"157100","divisionName":"柴河林业局","isLeaf":1},{"divisionCode":231083500,"post":"157100","divisionName":"海林农场","isLeaf":1},{"divisionCode":231083501,"post":"157100","divisionName":"山市种奶牛场","isLeaf":1}]