[{"divisionCode":350102001,"post":"350001","divisionName":"鼓东街道","isLeaf":1},{"divisionCode":350102002,"post":"350001","divisionName":"鼓西街道","isLeaf":1},{"divisionCode":350102003,"post":"350001","divisionName":"温泉街道","isLeaf":1},{"divisionCode":350102004,"post":"350001","divisionName":"东街街道","isLeaf":1},{"divisionCode":350102005,"post":"350001","divisionName":"南街街道","isLeaf":1},{"divisionCode":350102006,"post":"350001","divisionName":"安泰街道","isLeaf":1},{"divisionCode":350102007,"post":"350001","divisionName":"华大街道","isLeaf":1},{"divisionCode":350102008,"post":"350001","divisionName":"水部街道","isLeaf":1},{"divisionCode":350102009,"post":"350001","divisionName":"五凤街道","isLeaf":1},{"divisionCode":350102100,"post":"350001","divisionName":"洪山镇","isLeaf":1}]