[{"divisionCode":350124100,"post":"350800","divisionName":"梅城镇","isLeaf":1},{"divisionCode":350124101,"post":"350800","divisionName":"梅溪镇","isLeaf":1},{"divisionCode":350124102,"post":"350800","divisionName":"白樟镇","isLeaf":1},{"divisionCode":350124103,"post":"350800","divisionName":"金沙镇","isLeaf":1},{"divisionCode":350124104,"post":"350800","divisionName":"白中镇","isLeaf":1},{"divisionCode":350124105,"post":"350800","divisionName":"池园镇","isLeaf":1},{"divisionCode":350124106,"post":"350800","divisionName":"坂东镇","isLeaf":1},{"divisionCode":350124107,"post":"350800","divisionName":"塔庄镇","isLeaf":1},{"divisionCode":350124108,"post":"350800","divisionName":"省璜镇","isLeaf":1},{"divisionCode":350124109,"post":"350800","divisionName":"雄江镇","isLeaf":1},{"divisionCode":350124110,"post":"350800","divisionName":"东桥镇","isLeaf":1},{"divisionCode":350124200,"post":"350800","divisionName":"云龙乡","isLeaf":1},{"divisionCode":350124201,"post":"350800","divisionName":"上莲乡","isLeaf":1},{"divisionCode":350124204,"post":"350800","divisionName":"三溪乡","isLeaf":1},{"divisionCode":350124205,"post":"350800","divisionName":"桔林乡","isLeaf":1},{"divisionCode":350124206,"post":"350800","divisionName":"下祝乡","isLeaf":1}]