[{"divisionCode":410327100,"post":"471600","divisionName":"城关镇","isLeaf":1},{"divisionCode":410327102,"post":"471600","divisionName":"柳泉镇","isLeaf":1},{"divisionCode":410327103,"post":"471600","divisionName":"韩城镇","isLeaf":1},{"divisionCode":410327104,"post":"471600","divisionName":"白杨镇","isLeaf":1},{"divisionCode":410327105,"post":"471600","divisionName":"香鹿山镇","isLeaf":1},{"divisionCode":410327106,"post":"471600","divisionName":"锦屏镇","isLeaf":1},{"divisionCode":410327107,"post":"471600","divisionName":"三乡镇","isLeaf":1},{"divisionCode":410327108,"post":"471600","divisionName":"张坞镇","isLeaf":1},{"divisionCode":410327109,"post":"471600","divisionName":"莲庄镇","isLeaf":1},{"divisionCode":410327110,"post":"471600","divisionName":"赵保镇","isLeaf":1},{"divisionCode":410327111,"post":"471600","divisionName":"樊村镇","isLeaf":1},{"divisionCode":410327203,"post":"471600","divisionName":"盐镇乡","isLeaf":1},{"divisionCode":410327204,"post":"471600","divisionName":"高村乡","isLeaf":1},{"divisionCode":410327208,"post":"471600","divisionName":"花果山乡","isLeaf":1},{"divisionCode":410327209,"post":"471600","divisionName":"上观乡","isLeaf":1},{"divisionCode":410327212,"post":"471600","divisionName":"董王庄乡","isLeaf":1}]