[{"divisionCode":410303001,"post":"471000","divisionName":"王城路街道","isLeaf":1},{"divisionCode":410303002,"post":"471000","divisionName":"金谷园街道","isLeaf":1},{"divisionCode":410303003,"post":"471000","divisionName":"西工街道","isLeaf":1},{"divisionCode":410303004,"post":"471000","divisionName":"邙岭路街道","isLeaf":1},{"divisionCode":410303006,"post":"471000","divisionName":"唐宫路街道","isLeaf":1},{"divisionCode":410303007,"post":"471000","divisionName":"汉屯路街道","isLeaf":1},{"divisionCode":410303008,"post":"471000","divisionName":"凯旋东路街道","isLeaf":1},{"divisionCode":410303009,"post":"471000","divisionName":"洛北街道","isLeaf":1},{"divisionCode":410303010,"post":"471000","divisionName":"红山街道","isLeaf":1}]