[{"divisionCode":410883001,"post":"454750","divisionName":"大定街道","isLeaf":1},{"divisionCode":410883002,"post":"454750","divisionName":"会昌街道","isLeaf":1},{"divisionCode":410883003,"post":"454750","divisionName":"河雍街道","isLeaf":1},{"divisionCode":410883004,"post":"454750","divisionName":"河阳街道","isLeaf":1},{"divisionCode":410883100,"post":"454750","divisionName":"化工镇","isLeaf":1},{"divisionCode":410883101,"post":"454750","divisionName":"南庄镇","isLeaf":1},{"divisionCode":410883102,"post":"454750","divisionName":"城伯镇","isLeaf":1},{"divisionCode":410883103,"post":"454750","divisionName":"谷旦镇","isLeaf":1},{"divisionCode":410883104,"post":"454750","divisionName":"赵和镇","isLeaf":1},{"divisionCode":410883105,"post":"454750","divisionName":"西虢镇","isLeaf":1},{"divisionCode":410883201,"post":"454750","divisionName":"槐树乡","isLeaf":1}]