[{"divisionCode":411525001,"post":"465200","divisionName":"蓼城办事处","isLeaf":1},{"divisionCode":411525002,"post":"465200","divisionName":"番城办事处","isLeaf":1},{"divisionCode":411525003,"post":"465200","divisionName":"秀水办事处","isLeaf":1},{"divisionCode":411525101,"post":"465200","divisionName":"陈淋子镇","isLeaf":1},{"divisionCode":411525102,"post":"465200","divisionName":"黎集镇","isLeaf":1},{"divisionCode":411525103,"post":"465200","divisionName":"蒋集镇","isLeaf":1},{"divisionCode":411525104,"post":"465200","divisionName":"往流镇","isLeaf":1},{"divisionCode":411525105,"post":"465200","divisionName":"郭陆滩镇","isLeaf":1},{"divisionCode":411525106,"post":"465200","divisionName":"胡族铺镇","isLeaf":1},{"divisionCode":411525107,"post":"465200","divisionName":"方集镇","isLeaf":1},{"divisionCode":411525108,"post":"465200","divisionName":"三河尖镇","isLeaf":1},{"divisionCode":411525109,"post":"465200","divisionName":"段集镇","isLeaf":1},{"divisionCode":411525110,"post":"465200","divisionName":"汪棚镇","isLeaf":1},{"divisionCode":411525111,"post":"465200","divisionName":"张广庙镇","isLeaf":1},{"divisionCode":411525112,"post":"465200","divisionName":"陈集镇","isLeaf":1},{"divisionCode":411525113,"post":"465200","divisionName":"武庙集镇","isLeaf":1},{"divisionCode":411525114,"post":"465200","divisionName":"分水亭镇","isLeaf":1},{"divisionCode":411525115,"post":"465200","divisionName":"石佛店镇","isLeaf":1},{"divisionCode":411525116,"post":"465200","divisionName":"泉河铺镇","isLeaf":1},{"divisionCode":411525117,"post":"465200","divisionName":"祖师庙镇","isLeaf":1},{"divisionCode":411525201,"post":"465200","divisionName":"洪埠乡","isLeaf":1},{"divisionCode":411525202,"post":"465200","divisionName":"杨集乡","isLeaf":1},{"divisionCode":411525203,"post":"465200","divisionName":"马堽集乡","isLeaf":1},{"divisionCode":411525204,"post":"465200","divisionName":"草庙集乡","isLeaf":1},{"divisionCode":411525206,"post":"465200","divisionName":"南大桥乡","isLeaf":1},{"divisionCode":411525208,"post":"465200","divisionName":"赵岗乡","isLeaf":1},{"divisionCode":411525211,"post":"465200","divisionName":"张老埠乡","isLeaf":1},{"divisionCode":411525216,"post":"465200","divisionName":"沙河铺乡","isLeaf":1},{"divisionCode":411525218,"post":"465200","divisionName":"徐集乡","isLeaf":1},{"divisionCode":411525221,"post":"465200","divisionName":"李店乡","isLeaf":1},{"divisionCode":411525222,"post":"465200","divisionName":"丰港乡","isLeaf":1},{"divisionCode":411525223,"post":"465200","divisionName":"柳树店乡","isLeaf":1},{"divisionCode":411525224,"post":"465200","divisionName":"观堂乡","isLeaf":1}]