[{"divisionCode":430421100,"post":"421200","divisionName":"西渡镇","isLeaf":1},{"divisionCode":430421101,"post":"421200","divisionName":"集兵镇","isLeaf":1},{"divisionCode":430421103,"post":"421200","divisionName":"杉桥镇","isLeaf":1},{"divisionCode":430421104,"post":"421200","divisionName":"井头镇","isLeaf":1},{"divisionCode":430421105,"post":"421200","divisionName":"演陂镇","isLeaf":1},{"divisionCode":430421106,"post":"421200","divisionName":"金兰镇","isLeaf":1},{"divisionCode":430421107,"post":"421200","divisionName":"洪市镇","isLeaf":1},{"divisionCode":430421108,"post":"421200","divisionName":"曲兰镇","isLeaf":1},{"divisionCode":430421109,"post":"421200","divisionName":"金溪镇","isLeaf":1},{"divisionCode":430421110,"post":"421200","divisionName":"界牌镇","isLeaf":1},{"divisionCode":430421111,"post":"421200","divisionName":"渣江镇","isLeaf":1},{"divisionCode":430421112,"post":"421200","divisionName":"三湖镇","isLeaf":1},{"divisionCode":430421113,"post":"421200","divisionName":"台源镇","isLeaf":1},{"divisionCode":430421114,"post":"421200","divisionName":"关市镇","isLeaf":1},{"divisionCode":430421115,"post":"421200","divisionName":"库宗桥镇","isLeaf":1},{"divisionCode":430421116,"post":"421200","divisionName":"岘山镇","isLeaf":1},{"divisionCode":430421117,"post":"421200","divisionName":"石市镇","isLeaf":1},{"divisionCode":430421200,"post":"421200","divisionName":"樟木乡","isLeaf":1},{"divisionCode":430421201,"post":"421200","divisionName":"岣嵝乡","isLeaf":1},{"divisionCode":430421205,"post":"421200","divisionName":"栏垅乡","isLeaf":1},{"divisionCode":430421207,"post":"421200","divisionName":"大安乡","isLeaf":1},{"divisionCode":430421208,"post":"421200","divisionName":"溪江乡","isLeaf":1},{"divisionCode":430421210,"post":"421200","divisionName":"长安乡","isLeaf":1},{"divisionCode":430421211,"post":"421200","divisionName":"板市乡","isLeaf":1},{"divisionCode":430421212,"post":"421200","divisionName":"樟树乡","isLeaf":1},{"divisionCode":430421213,"post":"421200","divisionName":"潮江乡","isLeaf":1}]