[{"divisionCode":520603001,"post":"","divisionName":"谢桥街道","isLeaf":1},{"divisionCode":520603002,"post":"","divisionName":"茶店街道","isLeaf":1},{"divisionCode":520603100,"post":"","divisionName":"万山镇","isLeaf":1},{"divisionCode":520603200,"post":"","divisionName":"高楼坪侗族乡","isLeaf":1},{"divisionCode":520603201,"post":"","divisionName":"黄道侗族乡","isLeaf":1},{"divisionCode":520603202,"post":"","divisionName":"敖寨侗族乡","isLeaf":1},{"divisionCode":520603203,"post":"","divisionName":"下溪侗族乡","isLeaf":1},{"divisionCode":520603204,"post":"","divisionName":"鱼塘乡","isLeaf":1},{"divisionCode":520603205,"post":"","divisionName":"大坪乡","isLeaf":1}]